slingshot/__init__.py
slingshot/__vers.py
slingshot/api/__init__.py
slingshot/api/projects.py
slingshot/client.py
slingshot/types.py
c1s_slingshot_sdk_py-2.1.0.dist-info/licenses/LICENSE
c1s_slingshot_sdk_py-2.1.0.dist-info/licenses/NOTICE
c1s_slingshot_sdk_py-2.1.0.dist-info/WHEEL
c1s_slingshot_sdk_py-2.1.0.dist-info/METADATA
c1s_slingshot_sdk_py-2.1.0.dist-info/RECORD
