Metadata-Version: 2.4
Name: c1s-slingshot-sdk-py
Version: 2.1.0
Summary: Slingshot SDK
Author: Capital One Software
License-Expression: Apache-2.0
License-File: LICENSE
License-File: NOTICE
Classifier: Development Status :: 3 - Alpha
Classifier: Intended Audience :: Information Technology
Classifier: Intended Audience :: System Administrators
Classifier: Operating System :: OS Independent
Classifier: Programming Language :: Python :: 3 :: Only
Classifier: Programming Language :: Python :: 3
Classifier: Programming Language :: Python :: 3.10
Classifier: Programming Language :: Python
Requires-Dist: backoff>=2.2.1
Requires-Dist: httpx>=0.23
Requires-Dist: typing-extensions>=4.1.0
Requires-Dist: certifi>=2021.10.8
Requires-Dist: idna>=2.8
Requires-Dist: sniffio>=1.2.0
Requires-Dist: anyio>=2.0.0
Requires-Python: >=3.9, <3.14
Project-URL: Changelog, https://github.com/capitalone/c1s-slingshot-sdk-py/blob/main/docs/CHANGELOG.md
Project-URL: Home, https://github.com/capitalone/c1s-slingshot-sdk-py
